nteu_gateway/__init__.py
nteu_gateway/client.py
nteu_gateway/logger.py
nteu_gateway/nteu_gateway.py
nteu_gateway/nteu_gateway_name.py
nteu_gateway/server.py
nteu_gateway/translation_error.py
nteu_gateway/translation_task.py
nteu_gateway/translation_task_priority_queue.py
nteu_gateway/server_handler/__init__.py
nteu_gateway/server_handler/initialize.py
nteu_gateway/server_handler/translate.py
nteu_gateway/utils/__init__.py
nteu_gateway/utils/chunks.py
nteu_gateway-1.0.1.dist-info/METADATA
nteu_gateway-1.0.1.dist-info/WHEEL
nteu_gateway-1.0.1.dist-info/top_level.txt
nteu_gateway-1.0.1.dist-info/RECORD
